[
    {
        "content": [
            {
                "x": 2448.178956089478,
                "y": 300.64623032311516
            },
            {
                "x": 2761.352112676056,
                "y": 2550.4821872410935
            },
            {
                "x": 128.19221209610595,
                "y": 2775.96685998343
            },
            {
                "x": 371.2145816072907,
                "y": 273.0869925434963
            }
        ],
        "rectMask": {
            "xMin": 128.19221209610595,
            "yMin": 273.0869925434963,
            "width": 2633.1599005799503,
            "height": 2502.8798674399336
        },
        "labels": {
            "labelName": "board",
            "labelColor": "#ff0000",
            "labelColorRGB": "255,0,0",
            "visibility": false
        },
        "labelLocation": {
            "x": 1444.7721623860812,
            "y": 1524.526926263463
        },
        "contentType": "polygon"
    }
]